lina/__init__.py
Lina-1.0.10.dist-info/LICENSE.txt
Lina-1.0.10.dist-info/METADATA
Lina-1.0.10.dist-info/WHEEL
Lina-1.0.10.dist-info/top_level.txt
Lina-1.0.10.dist-info/RECORD
