Metadata-Version: 2.1
Name: Lina
Version: 1.0.10
Summary: Text template library
Home-page: http://shelter13.net/projects/Lina
Author: Matthäus G. Chajdas
Author-email: dev@anteru.net
License: BSD
Platform: UNKNOWN
Classifier: Development Status :: 6 - Mature
Classifier: Environment :: Console
Classifier: Intended Audience :: Developers
Classifier: License :: OSI Approved :: BSD License
Classifier: Natural Language :: English
Classifier: Operating System :: OS Independent
Classifier: Programming Language :: Python :: 3
Classifier: Programming Language :: Python :: 3.6
Classifier: Topic :: Software Development :: Pre-processors
Requires-Python: >=3.6
